{"originalText": "入院前3月，患者因结肠镜发现左半结肠肿瘤就诊于我院我科，于2015-09-23我院在全麻上行“剖腹探查、结肠癌根治术、肠粘连松解术”，手术顺利，术后予止血、预防性抗感染、补液、对症等治疗。术后病检（1508028）：（升结肠）粘液性腺癌，侵及全层，远、近切缘未见癌累及，肠周脂肪组织中淋巴结未见癌转移（0/8），（肠系膜结节）见癌组织（2枚），（腹膜结节）未见癌组织。术后恢复可，病情好转出院。于2015-10-20及2015-11-10在我科行化疗，目前患者无畏寒、发热，无咳嗽、咳痰，无恶心、呕吐，无腹痛、腹泻，无胸闷、胸痛、心悸等不适。患者为求第三次化疗，以“左半结肠癌术后3月，拟行第四次化疗”收入我科住院治疗。", "entities": [{"label_type": "疾病和诊断", "overlap": 0, "start_pos": 14, "end_pos": 20}, {"label_type": "手术", "overlap": 0, "start_pos": 47, "end_pos": 65}, {"label_type": "疾病和诊断", "overlap": 0, "start_pos": 108, "end_pos": 118}, {"label_type": "解剖部位", "overlap": 0, "start_pos": 135, "end_pos": 136}, {"label_type": "解剖部位", "overlap": 0, "start_pos": 157, "end_pos": 158}, {"label_type": "解剖部位", "overlap": 0, "start_pos": 173, "end_pos": 174}, {"end_pos": 253, "label_type": "解剖部位", "overlap": 0, "start_pos": 252}, {"end_pos": 256, "label_type": "解剖部位", "overlap": 0, "start_pos": 255}, {"end_pos": 260, "label_type": "解剖部位", "overlap": 0, "start_pos": 259}, {"end_pos": 263, "label_type": "解剖部位", "overlap": 0, "start_pos": 262}, {"end_pos": 266, "label_type": "解剖部位", "overlap": 0, "start_pos": 265}, {"label_type": "疾病和诊断", "overlap": 0, "start_pos": 283, "end_pos": 290}]}
