{"originalText": "2014-8因便血查胃镜示贲门占位，病理示中分化腺癌。当地行贲门癌根治术。术后给予吉西他滨+奈达铂*1，FOLFOX*6，末次化疗2015-2.间断中药治疗。2015-3发现肿标增高。2015-9-17CT示纵膈、残胃周围及腹膜后多发肿大淋巴结，肝内多发低密度密度灶，均考虑转移。两肺多发结节，考虑转移，盆腔积液。胃镜吻合口粘膜充血水肿，周围见结节样增生。距门齿25CM食管中段见1.5CM隆起型病变。病理示吻合口慢性炎，食管中段腺癌。目前患者进食欠佳，大小便正常，无黑便。体重稳定。", "entities": [{"label_type": "解剖部位", "overlap": 0, "start_pos": 13, "end_pos": 15}, {"label_type": "疾病和诊断", "overlap": 0, "start_pos": 21, "end_pos": 26}, {"end_pos": 36, "label_type": "手术", "overlap": 0, "start_pos": 30}, {"end_pos": 45, "label_type": "药物", "overlap": 0, "start_pos": 41}, {"end_pos": 49, "label_type": "药物", "overlap": 0, "start_pos": 46}, {"label_type": "影像检查", "overlap": 0, "start_pos": 101, "end_pos": 103}, {"end_pos": 106, "label_type": "解剖部位", "overlap": 0, "start_pos": 104}, {"end_pos": 109, "label_type": "解剖部位", "overlap": 0, "start_pos": 108}, {"label_type": "解剖部位", "overlap": 0, "start_pos": 112, "end_pos": 113}, {"end_pos": 124, "label_type": "解剖部位", "overlap": 0, "start_pos": 123}, {"end_pos": 142, "label_type": "解剖部位", "overlap": 0, "start_pos": 140}, {"label_type": "疾病和诊断", "overlap": 0, "start_pos": 152, "end_pos": 156}, {"end_pos": 181, "label_type": "解剖部位", "overlap": 0, "start_pos": 179}, {"end_pos": 189, "label_type": "解剖部位", "overlap": 0, "start_pos": 185}, {"label_type": "疾病和诊断", "overlap": 0, "start_pos": 211, "end_pos": 217}]}
